setup.py
util/__init__.py
util/bm25util.py
util/conceptutil.py
util/configutil.py
util/jiebautil.py
util/jsonutil.py
util/linereader.py
util/mongoutil.py
util/pdfutil.py
util/simutil.py
util/tfidfutil.py
util/translate.py
util/whooshutil.py
util/word2vec.py
yang0textutils.egg-info/PKG-INFO
yang0textutils.egg-info/SOURCES.txt
yang0textutils.egg-info/dependency_links.txt
yang0textutils.egg-info/top_level.txt
yang0textutils.egg-info/zip-safe