Metadata-Version: 1.1
Name: yang0textutils
Version: 0.0.1
Summary: this is a text package for yang0 personal.
Home-page: UNKNOWN
Author: yang0
Author-email: yang0@126.com
License: MIT
Keywords: text python package
Platform: UNKNOWN
Classifier: License :: OSI Approved :: MIT License
Classifier: Programming Language :: Python
Classifier: Intended Audience :: Developers
Classifier: Operating System :: OS Independent
